mongodb_connect/__init__.py
mongodb_connect/mongo_crud.py
test_mongo_connector-0.0.6.dist-info/METADATA
test_mongo_connector-0.0.6.dist-info/WHEEL
test_mongo_connector-0.0.6.dist-info/top_level.txt
test_mongo_connector-0.0.6.dist-info/RECORD
